chia_rs-0.36.0.dist-info/METADATA
chia_rs-0.36.0.dist-info/WHEEL
chia_rs.libs/libcrypto-3dc39733.so.1.1
chia_rs/__init__.py
chia_rs/chia_rs.cpython-312-aarch64-linux-gnu.so
chia_rs/chia_rs.pyi
chia_rs/datalayer.pyi
chia_rs/py.typed
chia_rs/sized_byte_class.py
chia_rs/sized_bytes.py
chia_rs/sized_ints.py
chia_rs/spend.py
chia_rs/struct_stream.py
chia_rs-0.36.0.dist-info/RECORD
