Metadata-Version: 2.4
Name: chia_rs
Version: 0.36.0
Requires-Dist: typing-extensions
Home-Page: https://github.com/Chia-Network/chia_rs
